datahero/__init__.py
datahero/explain.py
datahero/utils.py
datahero/viz.py
datahero-0.1.0.dist-info/licenses/LICENSE
datahero-0.1.0.dist-info/METADATA
datahero-0.1.0.dist-info/WHEEL
datahero-0.1.0.dist-info/top_level.txt
datahero-0.1.0.dist-info/RECORD
